custom_napalm/__init__.py
custom_napalm/base.py
custom_napalm/get.py
custom_napalm/models.py
custom_napalm/utils.py
custom_napalm/aoscx/__init__.py
custom_napalm/aoscx/aoscx.py
custom_napalm/eos/__init__.py
custom_napalm/eos/eos.py
custom_napalm/iosxr/__init__.py
custom_napalm/iosxr/iosxr.py
custom_napalm/iosxr/utils/textfsm_templates/controllers_optics.tpl
custom_napalm/iosxr/utils/textfsm_templates/sh_int_brief_phy.tpl
custom_napalm/iosxr/utils/textfsm_templates/sh_inventory.tpl
custom_napalm/iosxr_netconf/__init__.py
custom_napalm/iosxr_netconf/constants.py
custom_napalm/iosxr_netconf/iosxr.py
custom_napalm/junos/__init__.py
custom_napalm/junos/junos.py
custom_napalm/junos/junos_views.py
custom_napalm/junos/junos_views.yml
custom_napalm/nos/__init__.py
custom_napalm/nos/constants.py
custom_napalm/nos/nos.py
custom_napalm/nxos/__init__.py
custom_napalm/nxos/nxos.py
custom_napalm/nxos/utils/textfsm_templates/sh_int_transceiver.tpl
custom_napalm/nxos/utils/textfsm_templates/sh_inventory.tpl
custom_napalm/psimn/__init__.py
custom_napalm/psimn/psimn.py
custom_napalm/rls/__init__.py
custom_napalm/rls/rls.py
custom_napalm/saos/__init__.py
custom_napalm/saos/saos.py
custom_napalm/srl/__init__.py
custom_napalm/srl/srl.py
custom_napalm/sros/__init__.py
custom_napalm/sros/nc_filters.py
custom_napalm/sros/sros.py
custom_napalm/waveserver/__init__.py
custom_napalm/waveserver/waveserver.py
custom_napalm/waveserver/utils/textfsm_templates/chassis_inventory_show.tpl
custom_napalm/waveserver/utils/textfsm_templates/xcvr_diagnostics.tpl
custom_napalm/waveserver/utils/textfsm_templates/xcvr_show.tpl
sc_napalm-2.6.1.dist-info/METADATA
sc_napalm-2.6.1.dist-info/WHEEL
sc_napalm-2.6.1.dist-info/entry_points.txt
sc_napalm-2.6.1.dist-info/RECORD
