Metadata-Version: 2.4
Name: sc-napalm
Version: 2.6.1
Summary: Add your description here
Requires-Python: >=3.8
Requires-Dist: gitpython>=3.1.45
Requires-Dist: lxml>=6.0.2
Requires-Dist: napalm-ciena-saos>=0.1.0
Requires-Dist: napalm-srl>=1.0.5
Requires-Dist: napalm-sros>=1.0.2
Requires-Dist: napalm>=5.0.0
Requires-Dist: pyaoscx>=2.6.0
Requires-Dist: pynautobot>=2.1.1
Requires-Dist: python-decouple>=3.8
